bluer_ai/__init__.py
bluer_ai/__main__.py
bluer_ai/config.env
bluer_ai/env.py
bluer_ai/host.py
bluer_ai/logger.py
bluer_ai/sample.env
bluer_ai/.abcli/bluer_ai.sh
bluer_ai/.abcli/abcli/arg.sh
bluer_ai/.abcli/abcli/unpack.sh
bluer_ai/.abcli/bootstrap/dependencies.sh
bluer_ai/.abcli/bootstrap/logging.sh
bluer_ai/.abcli/bootstrap/paths.sh
bluer_ai/.abcli/bootstrap/system.sh
bluer_ai/.abcli/modules/abcli.sh
bluer_ai/.abcli/modules/init.sh
bluer_ai/.abcli/modules/initialize.sh
bluer_ai/.abcli/modules/plugins.sh
bluer_ai/.abcli/modules/terraform.sh
bluer_ai/.abcli/modules/plugins/install.sh
bluer_ai/.abcli/modules/plugins/transform.sh
bluer_ai/.abcli/modules/terraform/cat.sh
bluer_ai/.abcli/modules/terraform/get.sh
bluer_ai/.abcli/plugins/GPU.sh
bluer_ai/.abcli/plugins/actions.sh
bluer_ai/.abcli/plugins/alias.sh
bluer_ai/.abcli/plugins/build_README.sh
bluer_ai/.abcli/plugins/conda.sh
bluer_ai/.abcli/plugins/git.sh
bluer_ai/.abcli/plugins/latex.sh
bluer_ai/.abcli/plugins/pypi.sh
bluer_ai/.abcli/plugins/screen.sh
bluer_ai/.abcli/plugins/session.sh
bluer_ai/.abcli/plugins/ssh.sh
bluer_ai/.abcli/plugins/vscode.sh
bluer_ai/.abcli/plugins/web.sh
bluer_ai/.abcli/plugins/wifi.sh
bluer_ai/.abcli/plugins/conda/create.sh
bluer_ai/.abcli/plugins/conda/exists.sh
bluer_ai/.abcli/plugins/conda/list.sh
bluer_ai/.abcli/plugins/conda/rm.sh
bluer_ai/.abcli/plugins/git/browse.sh
bluer_ai/.abcli/plugins/git/checkout.sh
bluer_ai/.abcli/plugins/git/clone.sh
bluer_ai/.abcli/plugins/git/create_branch.sh
bluer_ai/.abcli/plugins/git/get_remote.sh
bluer_ai/.abcli/plugins/git/get_repo_name.sh
bluer_ai/.abcli/plugins/git/increment_version.sh
bluer_ai/.abcli/plugins/git/pull.sh
bluer_ai/.abcli/plugins/git/push.sh
bluer_ai/.abcli/plugins/git/review.sh
bluer_ai/.abcli/plugins/git/rm.sh
bluer_ai/.abcli/plugins/git/seed.sh
bluer_ai/.abcli/plugins/git/set_remote.sh
bluer_ai/.abcli/plugins/git/status.sh
bluer_ai/.abcli/plugins/git/utils.sh
bluer_ai/.abcli/plugins/latex/bibclean.sh
bluer_ai-12.538.1.dist-info/METADATA
bluer_ai-12.538.1.dist-info/WHEEL
bluer_ai-12.538.1.dist-info/top_level.txt
bluer_ai-12.538.1.dist-info/RECORD
