Metadata-Version: 2.4
Name: bluer_ai
Version: 12.538.1
Summary: 🌀 A language to speak AI.
Home-page: https://github.com/kamangir/bluer-ai
Author: Arash Abadpour (Kamangir)
Author-email: arash.abadpour@gmail.com
License: CC0-1.0
Classifier: Programming Language :: Python :: 3
Classifier: Programming Language :: Unix Shell
Classifier: Operating System :: OS Independent
Requires-Dist: importlib-metadata
Requires-Dist: blueness
Requires-Dist: bluer-options
Requires-Dist: bluer-objects
Dynamic: author
Dynamic: author-email
Dynamic: classifier
Dynamic: description
Dynamic: description-content-type
Dynamic: home-page
Dynamic: license
Dynamic: requires-dist
Dynamic: summary
